invokeai_models_cli/__init__.py
invokeai_models_cli/__main__.py
invokeai_models_cli/__version__.py
invokeai_models_cli/cli.py
invokeai_models_cli/functions.py
invokeai_models_cli/helpers.py
invokeai_models_cli/snapshots/database_models_cache.json
invokeai_models_cli/snapshots/local_models_cache.json
invokeai_models_cli/snapshots/sharp_star_2024-11-20 09-21-01.db
invokeai_models_cli/snapshots/snapshots.json
invokeai_models_cli/snapshots/wise_lion_2024-09-27 10-37-18.db
invokeai_models_cli-1.3.1.dist-info/METADATA
invokeai_models_cli-1.3.1.dist-info/WHEEL
invokeai_models_cli-1.3.1.dist-info/entry_points.txt
invokeai_models_cli-1.3.1.dist-info/licenses/LICENSE
invokeai_models_cli-1.3.1.dist-info/RECORD
