Metadata-Version: 2.3
Name: invokeai_models_cli
Version: 1.3.1
Summary: CLI tool for working with orphaned external models and the InvokeAI database
Project-URL: Repository, https://github.com/regiellis/invokeai_models_cli
Project-URL: Documentation, https://github.com/regiellis/invokeai_models_cli/blob/main/README.md
Project-URL: Bug Tracker, https://github.com/regiellis/invokeai_models_cli/issues
Author-email: Regi E <regi@bynine.io>
License: Copyright 2024 Regi E Ellis
Keywords: ai,cli,generative-ai,invokeai
Classifier: License :: OSI Approved :: Apache Software License
Classifier: Operating System :: OS Independent
Classifier: Programming Language :: Python :: 3.10
Requires-Python: >=3.10
Requires-Dist: httpx
Requires-Dist: inquirer
Requires-Dist: packaging
Requires-Dist: pytest
Requires-Dist: python-dotenv
Requires-Dist: rich
Requires-Dist: shellingham
Requires-Dist: typer
